aws2wrap/__init__.py
aws2wrap/version.py
aws2_wrap-1.4.0.dist-info/LICENSE
aws2_wrap-1.4.0.dist-info/METADATA
aws2_wrap-1.4.0.dist-info/WHEEL
aws2_wrap-1.4.0.dist-info/entry_points.txt
aws2_wrap-1.4.0.dist-info/top_level.txt
aws2_wrap-1.4.0.dist-info/RECORD
