Metadata-Version: 2.1
Name: aws2-wrap
Version: 1.4.0
Summary: A wrapper for executing a command with AWS CLI v2 and SSO
Home-page: https://github.com/linaro-its/aws2-wrap
Author: Philip Colmer
Author-email: it-support@linaro.org
License: GPL-3.0-or-later
Keywords: aws profile sso assume role
Platform: UNKNOWN
Classifier: Development Status :: 5 - Production/Stable
Classifier: Intended Audience :: Developers
Classifier: Programming Language :: Python :: 3
Classifier: Environment :: Console
Classifier: License :: OSI Approved :: GNU General Public License v3 (GPLv3)
Classifier: Operating System :: OS Independent
Requires-Python: >=3.8
License-File: LICENSE
Requires-Dist: psutil
